{"info":{"file":"src/client/components/Preferences.js","fileShort":"client/components/Preferences.js","fileSafe":"client_components_Preferences_js","link":"files/client_components_Preferences_js/index.html"},"complexity":{"methodAggregate":{"cyclomatic":1,"cyclomaticDensity":1.515,"halstead":{"bugs":0.735,"difficulty":18.409,"effort":40591.382,"length":338,"time":2255.077,"vocabulary":92,"volume":2204.964,"operands":{"distinct":77,"total":189,"identifiers":["__stripped__"]},"operators":{"distinct":15,"total":149,"identifiers":["__stripped__"]}},"params":11,"sloc":{"logical":66,"physical":146}},"settings":{"commonjs":false,"forin":false,"logicalor":true,"switchcase":true,"trycatch":false,"newmi":true},"classes":[],"dependencies":[{"line":1,"path":"react","type":"esm"},{"line":2,"path":"@material-ui/core/styles","type":"esm"},{"line":3,"path":"@material-ui/core/Container","type":"esm"},{"line":4,"path":"@material-ui/core/Slider","type":"esm"},{"line":5,"path":"@material-ui/core/FormControl","type":"esm"},{"line":6,"path":"@material-ui/core/FormLabel","type":"esm"}],"errors":[],"lineEnd":146,"lineStart":1,"maintainability":68.22,"methods":[{"cyclomatic":1,"cyclomaticDensity":8.333,"halstead":{"bugs":0.075,"difficulty":2.842,"effort":642.822,"length":50,"time":35.712,"vocabulary":23,"volume":226.178,"operands":{"distinct":19,"total":27,"identifiers":["__stripped__"]},"operators":{"distinct":4,"total":23,"identifiers":["__stripped__"]}},"params":1,"sloc":{"logical":12,"physical":18},"errors":[],"lineEnd":37,"lineStart":20,"name":"<anonymous>","complexity":{"cyclomatic":1,"sloc":{"logical":12,"physical":18},"halstead":{"bugs":0.075,"difficulty":2.842,"effort":642.822,"length":50,"time":35.712,"vocabulary":23,"volume":226.178,"operands":{"distinct":19,"total":27,"identifiers":["__stripped__"]},"operators":{"distinct":4,"total":23,"identifiers":["__stripped__"]}}},"line":20},{"cyclomatic":1,"cyclomaticDensity":100,"halstead":{"bugs":0.001,"difficulty":1,"effort":3,"length":3,"time":0.167,"vocabulary":2,"volume":3,"operands":{"distinct":1,"total":2,"identifiers":["__stripped__"]},"operators":{"distinct":1,"total":1,"identifiers":["__stripped__"]}},"params":1,"sloc":{"logical":1,"physical":3},"errors":[],"lineEnd":65,"lineStart":63,"name":"valuetext","complexity":{"cyclomatic":1,"sloc":{"logical":1,"physical":3},"halstead":{"bugs":0.001,"difficulty":1,"effort":3,"length":3,"time":0.167,"vocabulary":2,"volume":3,"operands":{"distinct":1,"total":2,"identifiers":["__stripped__"]},"operators":{"distinct":1,"total":1,"identifiers":["__stripped__"]}}},"line":63},{"cyclomatic":1,"cyclomaticDensity":8.333,"halstead":{"bugs":0.163,"difficulty":13.895,"effort":6804.995,"length":103,"time":378.055,"vocabulary":27,"volume":489.753,"operands":{"distinct":19,"total":66,"identifiers":["__stripped__"]},"operators":{"distinct":8,"total":37,"identifiers":["__stripped__"]}},"params":1,"sloc":{"logical":12,"physical":77},"errors":[],"lineEnd":145,"lineStart":69,"name":"RadioButtonsGroup","complexity":{"cyclomatic":1,"sloc":{"logical":12,"physical":77},"halstead":{"bugs":0.163,"difficulty":13.895,"effort":6804.995,"length":103,"time":378.055,"vocabulary":27,"volume":489.753,"operands":{"distinct":19,"total":66,"identifiers":["__stripped__"]},"operators":{"distinct":8,"total":37,"identifiers":["__stripped__"]}}},"line":69},{"cyclomatic":1,"cyclomaticDensity":20,"halstead":{"bugs":0.022,"difficulty":3.125,"effort":208.15,"length":18,"time":11.564,"vocabulary":13,"volume":66.608,"operands":{"distinct":8,"total":10,"identifiers":["__stripped__"]},"operators":{"distinct":5,"total":8,"identifiers":["__stripped__"]}},"params":2,"sloc":{"logical":5,"physical":4},"errors":[],"lineEnd":85,"lineStart":82,"name":"<anonymous>","complexity":{"cyclomatic":1,"sloc":{"logical":5,"physical":4},"halstead":{"bugs":0.022,"difficulty":3.125,"effort":208.15,"length":18,"time":11.564,"vocabulary":13,"volume":66.608,"operands":{"distinct":8,"total":10,"identifiers":["__stripped__"]},"operators":{"distinct":5,"total":8,"identifiers":["__stripped__"]}}},"line":82},{"cyclomatic":1,"cyclomaticDensity":20,"halstead":{"bugs":0.022,"difficulty":3.125,"effort":208.15,"length":18,"time":11.564,"vocabulary":13,"volume":66.608,"operands":{"distinct":8,"total":10,"identifiers":["__stripped__"]},"operators":{"distinct":5,"total":8,"identifiers":["__stripped__"]}},"params":2,"sloc":{"logical":5,"physical":4},"errors":[],"lineEnd":102,"lineStart":99,"name":"<anonymous>","complexity":{"cyclomatic":1,"sloc":{"logical":5,"physical":4},"halstead":{"bugs":0.022,"difficulty":3.125,"effort":208.15,"length":18,"time":11.564,"vocabulary":13,"volume":66.608,"operands":{"distinct":8,"total":10,"identifiers":["__stripped__"]},"operators":{"distinct":5,"total":8,"identifiers":["__stripped__"]}}},"line":99},{"cyclomatic":1,"cyclomaticDensity":20,"halstead":{"bugs":0.022,"difficulty":3.125,"effort":208.15,"length":18,"time":11.564,"vocabulary":13,"volume":66.608,"operands":{"distinct":8,"total":10,"identifiers":["__stripped__"]},"operators":{"distinct":5,"total":8,"identifiers":["__stripped__"]}},"params":2,"sloc":{"logical":5,"physical":4},"errors":[],"lineEnd":118,"lineStart":115,"name":"<anonymous>","complexity":{"cyclomatic":1,"sloc":{"logical":5,"physical":4},"halstead":{"bugs":0.022,"difficulty":3.125,"effort":208.15,"length":18,"time":11.564,"vocabulary":13,"volume":66.608,"operands":{"distinct":8,"total":10,"identifiers":["__stripped__"]},"operators":{"distinct":5,"total":8,"identifiers":["__stripped__"]}}},"line":115},{"cyclomatic":1,"cyclomaticDensity":20,"halstead":{"bugs":0.022,"difficulty":3.125,"effort":208.15,"length":18,"time":11.564,"vocabulary":13,"volume":66.608,"operands":{"distinct":8,"total":10,"identifiers":["__stripped__"]},"operators":{"distinct":5,"total":8,"identifiers":["__stripped__"]}},"params":2,"sloc":{"logical":5,"physical":4},"errors":[],"lineEnd":135,"lineStart":132,"name":"<anonymous>","complexity":{"cyclomatic":1,"sloc":{"logical":5,"physical":4},"halstead":{"bugs":0.022,"difficulty":3.125,"effort":208.15,"length":18,"time":11.564,"vocabulary":13,"volume":66.608,"operands":{"distinct":8,"total":10,"identifiers":["__stripped__"]},"operators":{"distinct":5,"total":8,"identifiers":["__stripped__"]}}},"line":132}],"methodAverage":{"cyclomatic":1,"cyclomaticDensity":28.095,"halstead":{"bugs":0.047,"difficulty":4.32,"effort":1183.345,"length":32.571,"time":65.741,"vocabulary":14.857,"volume":140.766,"operands":{"distinct":10.143,"total":19.286},"operators":{"distinct":4.714,"total":13.286}},"params":1.571,"sloc":{"logical":6.429,"physical":16.286}},"module":"client/components/Preferences.js","aggregate":{"complexity":{"cyclomatic":1,"cyclomaticDensity":1.515,"halstead":{"bugs":0.735,"difficulty":18.409,"effort":40591.382,"length":338,"time":2255.077,"vocabulary":92,"volume":2204.964,"operands":{"distinct":77,"total":189,"identifiers":["__stripped__"]},"operators":{"distinct":15,"total":149,"identifiers":["__stripped__"]}},"params":11,"sloc":{"logical":66,"physical":146}}},"functions":[{"cyclomatic":1,"cyclomaticDensity":8.333,"halstead":{"bugs":0.075,"difficulty":2.842,"effort":642.822,"length":50,"time":35.712,"vocabulary":23,"volume":226.178,"operands":{"distinct":19,"total":27,"identifiers":["__stripped__"]},"operators":{"distinct":4,"total":23,"identifiers":["__stripped__"]}},"params":1,"sloc":{"logical":12,"physical":18},"errors":[],"lineEnd":37,"lineStart":20,"name":"<anonymous>","complexity":{"cyclomatic":1,"sloc":{"logical":12,"physical":18},"halstead":{"bugs":0.075,"difficulty":2.842,"effort":642.822,"length":50,"time":35.712,"vocabulary":23,"volume":226.178,"operands":{"distinct":19,"total":27,"identifiers":["__stripped__"]},"operators":{"distinct":4,"total":23,"identifiers":["__stripped__"]}}},"line":20},{"cyclomatic":1,"cyclomaticDensity":100,"halstead":{"bugs":0.001,"difficulty":1,"effort":3,"length":3,"time":0.167,"vocabulary":2,"volume":3,"operands":{"distinct":1,"total":2,"identifiers":["__stripped__"]},"operators":{"distinct":1,"total":1,"identifiers":["__stripped__"]}},"params":1,"sloc":{"logical":1,"physical":3},"errors":[],"lineEnd":65,"lineStart":63,"name":"valuetext","complexity":{"cyclomatic":1,"sloc":{"logical":1,"physical":3},"halstead":{"bugs":0.001,"difficulty":1,"effort":3,"length":3,"time":0.167,"vocabulary":2,"volume":3,"operands":{"distinct":1,"total":2,"identifiers":["__stripped__"]},"operators":{"distinct":1,"total":1,"identifiers":["__stripped__"]}}},"line":63},{"cyclomatic":1,"cyclomaticDensity":8.333,"halstead":{"bugs":0.163,"difficulty":13.895,"effort":6804.995,"length":103,"time":378.055,"vocabulary":27,"volume":489.753,"operands":{"distinct":19,"total":66,"identifiers":["__stripped__"]},"operators":{"distinct":8,"total":37,"identifiers":["__stripped__"]}},"params":1,"sloc":{"logical":12,"physical":77},"errors":[],"lineEnd":145,"lineStart":69,"name":"RadioButtonsGroup","complexity":{"cyclomatic":1,"sloc":{"logical":12,"physical":77},"halstead":{"bugs":0.163,"difficulty":13.895,"effort":6804.995,"length":103,"time":378.055,"vocabulary":27,"volume":489.753,"operands":{"distinct":19,"total":66,"identifiers":["__stripped__"]},"operators":{"distinct":8,"total":37,"identifiers":["__stripped__"]}}},"line":69},{"cyclomatic":1,"cyclomaticDensity":20,"halstead":{"bugs":0.022,"difficulty":3.125,"effort":208.15,"length":18,"time":11.564,"vocabulary":13,"volume":66.608,"operands":{"distinct":8,"total":10,"identifiers":["__stripped__"]},"operators":{"distinct":5,"total":8,"identifiers":["__stripped__"]}},"params":2,"sloc":{"logical":5,"physical":4},"errors":[],"lineEnd":85,"lineStart":82,"name":"<anonymous>","complexity":{"cyclomatic":1,"sloc":{"logical":5,"physical":4},"halstead":{"bugs":0.022,"difficulty":3.125,"effort":208.15,"length":18,"time":11.564,"vocabulary":13,"volume":66.608,"operands":{"distinct":8,"total":10,"identifiers":["__stripped__"]},"operators":{"distinct":5,"total":8,"identifiers":["__stripped__"]}}},"line":82},{"cyclomatic":1,"cyclomaticDensity":20,"halstead":{"bugs":0.022,"difficulty":3.125,"effort":208.15,"length":18,"time":11.564,"vocabulary":13,"volume":66.608,"operands":{"distinct":8,"total":10,"identifiers":["__stripped__"]},"operators":{"distinct":5,"total":8,"identifiers":["__stripped__"]}},"params":2,"sloc":{"logical":5,"physical":4},"errors":[],"lineEnd":102,"lineStart":99,"name":"<anonymous>","complexity":{"cyclomatic":1,"sloc":{"logical":5,"physical":4},"halstead":{"bugs":0.022,"difficulty":3.125,"effort":208.15,"length":18,"time":11.564,"vocabulary":13,"volume":66.608,"operands":{"distinct":8,"total":10,"identifiers":["__stripped__"]},"operators":{"distinct":5,"total":8,"identifiers":["__stripped__"]}}},"line":99},{"cyclomatic":1,"cyclomaticDensity":20,"halstead":{"bugs":0.022,"difficulty":3.125,"effort":208.15,"length":18,"time":11.564,"vocabulary":13,"volume":66.608,"operands":{"distinct":8,"total":10,"identifiers":["__stripped__"]},"operators":{"distinct":5,"total":8,"identifiers":["__stripped__"]}},"params":2,"sloc":{"logical":5,"physical":4},"errors":[],"lineEnd":118,"lineStart":115,"name":"<anonymous>","complexity":{"cyclomatic":1,"sloc":{"logical":5,"physical":4},"halstead":{"bugs":0.022,"difficulty":3.125,"effort":208.15,"length":18,"time":11.564,"vocabulary":13,"volume":66.608,"operands":{"distinct":8,"total":10,"identifiers":["__stripped__"]},"operators":{"distinct":5,"total":8,"identifiers":["__stripped__"]}}},"line":115},{"cyclomatic":1,"cyclomaticDensity":20,"halstead":{"bugs":0.022,"difficulty":3.125,"effort":208.15,"length":18,"time":11.564,"vocabulary":13,"volume":66.608,"operands":{"distinct":8,"total":10,"identifiers":["__stripped__"]},"operators":{"distinct":5,"total":8,"identifiers":["__stripped__"]}},"params":2,"sloc":{"logical":5,"physical":4},"errors":[],"lineEnd":135,"lineStart":132,"name":"<anonymous>","complexity":{"cyclomatic":1,"sloc":{"logical":5,"physical":4},"halstead":{"bugs":0.022,"difficulty":3.125,"effort":208.15,"length":18,"time":11.564,"vocabulary":13,"volume":66.608,"operands":{"distinct":8,"total":10,"identifiers":["__stripped__"]},"operators":{"distinct":5,"total":8,"identifiers":["__stripped__"]}}},"line":132}]},"eslint":{"messages":[]}}